evtt
