Metadata-Version: 2.1
Name: evtt
Version: 1.22
Summary: Django app for vosk
Home-page: https://github.com/epg900/pvss.git
Author: epg
Author-email: epg900@gmail.com
License: GNU GENERAL PUBLIC LICENSE
Requires-Python: >=3.7
License-File: LICENSE
